ecopann/__init__.py
ecopann/ann.py
ecopann/cosmic_params.py
ecopann/data_processor.py
ecopann/data_simulator.py
ecopann/element.py
ecopann/evaluate.py
ecopann/fcnet.py
ecopann/hpmodel.py
ecopann/models.py
ecopann/nodeframe.py
ecopann/optimize.py
ecopann/plotter.py
ecopann/sequence.py
ecopann/space_updater.py
ecopann/train.py
ecopann/utils.py
ecopann/coplot/__init__.py
ecopann/coplot/plot_contours.py
ecopann/coplot/plot_settings.py
ecopann/coplot/plots.py
ecopann/coplot/utils.py
ecopann-1.1.1.data/data/Union2.1.txt
ecopann-1.1.1.data/data/chain_fwCDM_2params.npy
examples/predict_SNe_BAO.py
examples/predict_linear.py
examples/predict_union2.1.py
examples/simulator.py
examples/train_SNe_BAO.py
examples/train_linear.py
examples/train_union2.1.py
examples/data/Union2.1.txt
examples/data/MCMC_chains/chain_fwCDM_2params.npy
ecopann-1.1.1.dist-info/METADATA
ecopann-1.1.1.dist-info/WHEEL
ecopann-1.1.1.dist-info/top_level.txt
ecopann-1.1.1.dist-info/RECORD
