Metadata-Version: 2.1
Name: ecopann
Version: 1.1.1
Summary: Estimating Cosmological Parameters with Artificial Neural Network
Home-page: UNKNOWN
Author: Guojian Wang
Author-email: gjwang@mail.bnu.edu.cn
License: MIT
Keywords: pip,ANN
Platform: any
